prymer/__init__.py
prymer/api/__init__.py
prymer/api/clustering.py
prymer/api/coordmath.py
prymer/api/melting.py
prymer/api/minoptmax.py
prymer/api/oligo.py
prymer/api/oligo_like.py
prymer/api/picking.py
prymer/api/primer.py
prymer/api/primer_pair.py
prymer/api/span.py
prymer/api/variant_lookup.py
prymer/ntthal/__init__.py
prymer/offtarget/__init__.py
prymer/offtarget/bwa.py
prymer/offtarget/offtarget_detector.py
prymer/primer3/__init__.py
prymer/primer3/primer3.py
prymer/primer3/primer3_failure_reason.py
prymer/primer3/primer3_input.py
prymer/primer3/primer3_input_tag.py
prymer/primer3/primer3_parameters.py
prymer/primer3/primer3_task.py
prymer/primer3/primer3_weights.py
prymer/py.typed
prymer/util/__init__.py
prymer/util/executable_runner.py
prymer-3.0.0.dist-info/LICENSE
prymer-3.0.0.dist-info/METADATA
prymer-3.0.0.dist-info/WHEEL
prymer-3.0.0.dist-info/RECORD
