Metadata-Version: 2.3
Name: prymer
Version: 3.0.0
Summary: Python primer design library
License: MIT
Keywords: bioinformatics,genomics,dna
Author: Yossi Farjoun
Author-email: yossi@fulcrumgenomics.com
Requires-Python: >=3.11,<4.0
Classifier: Development Status :: 3 - Alpha
Classifier: Environment :: Console
Classifier: Intended Audience :: Developers
Classifier: Intended Audience :: Science/Research
Classifier: License :: OSI Approved :: MIT License
Classifier: Operating System :: OS Independent
Classifier: Programming Language :: Python :: 3
Classifier: Programming Language :: Python :: 3.11
Classifier: Programming Language :: Python :: 3.12
Classifier: Programming Language :: Python :: 3.13
Classifier: Topic :: Scientific/Engineering :: Bio-Informatics
Classifier: Topic :: Software Development :: Documentation
Classifier: Topic :: Software Development :: Libraries :: Python Modules
Requires-Dist: fgpyo (>=0.8.0,<0.9.0)
Requires-Dist: ordered-set (>=4.1.0,<5.0.0)
Requires-Dist: pybedlite (>=1.0.0,<2.0.0)
Requires-Dist: pyproject_hooks (>=1.0.0,<2.0.0,!=1.1.0)
Requires-Dist: pysam (>=0.22.1,<0.23.0)
Requires-Dist: strenum (>=0.4.15,<0.5.0)
Project-URL: Bug Tracker, https://github.com/fulcrumgenomics/prymer/issues
Project-URL: Documentation, https://github.com/fulcrumgenomics/prymer
Project-URL: Homepage, https://github.com/fulcrumgenomics/prymer
Project-URL: Repository, https://github.com/fulcrumgenomics/prymer
